{
  "greeting": "Hy 👋",
  "name": "Zahraa Farzadila",
  "greetingText": "Gue tau lo sibuk bangett",
  "wishText": "guee berharap bangett lo tetep semangat yaa walaupun se hectic apapunn :))",
  "imagePath": "./img/profile.jpg",
  "text1": "semangat ngejalanin aktivitas hari ini yaaa :D",
  "textInChatBox": "semangat yaaa ngejalanin hari ini sama besok kalo full bangett",
  "sendButtonLabel": "Send",
  "text2": "gue gatau mau ngetik apa lagii",
  "text3": "yang penting semangat yaaa",
  "text4": "semoga ini bisa bikin lo naikin mood yaa walaupun",
  "text4Adjective": "engga terlalu bagus",
  "text5Entry": "Karena,",
  "text5Content": "lo itu keren raa",
  "smiley": ":)",
  "text6Content": "That's why I made it",
  "bigTextPart1": "S",
  "bigTextPart2": "O",
  "wishHeading": "jangan pusing pusing!!!",
  "outroText": "Okay, now come back and tell me if you liked it.",
  "replayText": "Or click this, kalau lo mau lihat dari awal lagi.",
  "outroSmiley": ":)"
}
